{"status": "ok", "totalResults": 35, "articles": [{"source": {"id": null, "name": "Mt.co.kr"}, "author": "\uae40\ub3d9\uc724", "title": "'\uba54\uc2dc, \ubb34\uad00 \uc124\uc6c0 \ud480\uc5c8\ub2e4' \uc544\ub974\ud5e8\ud2f0\ub098, \ube0c\ub77c\uc9c8 \uaebe\uace0 \ucf54\ud30c \uc6b0\uc2b9... \ub514\ub9c8\ub9ac\uc544 \uacb0\uc2b9\uace8 - \uba38\ub2c8\ud22c\ub370\uc774", "description": "\uc544\ub974\ud5e8\ud2f0\ub098\uac00 \uac1c\ucd5c\uad6d\uc774\uc790 \uc219\uc801 \ube0c\ub77c\uc9c8\uc744 \uaebe\uace0 \ucf54\ud30c \uc544\uba54\ub9ac\uce74 \uc6b0\uc2b9\uc744 \ub2ec\uc131\ud588\ub2e4. \uadf8\ub3d9\uc548 \uc131\uc778\uad6d\uac00\ub300\ud45c\ud300\uc5d0\uc11c \uc6b0\uc2b9\uc774 \uc5c6\ub358 \ub9ac\uc624\ub12c \uba54\uc2dc(34)\ub294 \ub9c8\uce68\ub0b4 \ubb34\uad00\uc758 \uc124\uc6c0\uc744 \ud574\uc18c\ud588\ub2e4....", "url": "https://news.mt.co.kr/mtview.php?no=2021071111020596269", "urlToImage": "https://thumb.mt.co.kr/21/2021/07/2021071111020596269_1.jpg", "publishedAt": "2021-07-11T02:39:12Z", "content": ". (34) .11() 2021 22 1-0 . \r\n1993 28 15 . \r\n. \r\n2004 FC 10, UEFA 4, 7 . \r\n. 2014 , 3 (2007, 2015, 2016) .\r\n. 1 , 2 . \r\n4 2 1 8 , 8 1 2 . 4 .\r\n, 4 5 MVP . , , ."}, {"source": {"id": null, "name": "Sportsw.kr"}, "author": "\uc2a4\ud3ec\uce20W(Sports W)", "title": "[LPGA] \ud558\ud0c0\uc624\uce74 \ub098\uc0ac, \ub9c8\ub77c\ud1a4 \ud074\ub798\uc2dd \uc0ac\ud758\uc9f8 \uc120\ub450...\uc591\ud76c\uc601 \uacf5\ub3d9 5\uc704 \u2032\uc810\ud504\u2032 - \uc2a4\ud3ec\uce20W", "description": "\u25b2 \ud558\ud0c0\uc624\uce74 \ub098\uc0ac(\uc0ac\uc9c4: AP=\uc5f0\ud569\ub274\uc2a4) \ud558\ud0c0\uc624\uce74 \ub098\uc0ac(\uc77c\ubcf8)\uac00 \ubbf8\uad6d\uc5ec\uc790\ud504\ub85c\uace8\ud504(LPGA) ...", "url": "https://sportsw.kr/news/newsview.php?ncode=1065579881596013", "urlToImage": "http://sportsw.kr/news/data/20210711/p1065579881596013_181_thum.jpg", "publishedAt": "2021-07-11T02:24:14Z", "content": "()\u00a0(LPGA) ( 200 ) .\u00a0\r\n\u00a011() (71) 3\u00a07 \u00a019 194 , .\u00a0\r\n , ( ) 2(13 200) 6 .\r\nLPGA 3 11 5 ' LPGA ' 9 US .\u00a0 2019 .\r\n \u00a0 7 1 6 65 \u00a0 11 202 , 22 5 .\r\n28 KMPG PGA 9 \u00a02 10 .\u00a0\r\n LPGA 5 . 3(2015\u00b72017\u00b72019 ), 1(20\u2026 [+26 chars]"}, {"source": {"id": "google-news", "name": "Google News"}, "author": null, "title": "'\ud655\uc9c4\uc790 \ubc1c\uc0dd' \ud504\ub85c\uc57c\uad6c \uba48\ucd94\ub098?...KBO \uae34\uae09 \uc2e4\ud589\uc704\uc6d0\ud68c \uac1c\ucd5c / YTN - YTN news", "description": null, "url": "https://news.google.com/__i/rss/rd/articles/CBMiK2h0dHBzOi8vd3d3LnlvdXR1YmUuY29tL3dhdGNoP3Y9NEZaN0d4SkhaMVHSAQA?oc=5", "urlToImage": null, "publishedAt": "2021-07-11T02:01:26Z", "content": null}, {"source": {"id": "google-news", "name": "Google News"}, "author": null, "title": "\ub3c4\ucfc4\uc62c\ub9bc\ud53d \ud6c4\ucfe0\uc2dc\ub9c8\ub3c4 \ubb34\uad00\uc911 \uacbd\uae30\ub85c \ubcc0\uacbd / \uc5f0\ud569\ub274\uc2a4TV (YonhapnewsTV) - \uc5f0\ud569\ub274\uc2a4TV", "description": null, "url": "https://news.google.com/__i/rss/rd/articles/CBMiK2h0dHBzOi8vd3d3LnlvdXR1YmUuY29tL3dhdGNoP3Y9S3R1M2NUcTBTQzDSAQA?oc=5", "urlToImage": null, "publishedAt": "2021-07-11T01:17:57Z", "content": null}, {"source": {"id": null, "name": "Chosun.com"}, "author": null, "title": "\uae40\ub3d9\uc131 \u201c\uc591\uc721\ube44 \ubabb \uc8fc\uace0 \uc788\ub294 \uac83\u201d \uc8fc\uc7a5\u2192\uc778\ubbfc\uc815 \u201c\ubc24\uc774 \ub05d\ub0b4\uc918\uc11c \ub9cc\ub098? \uae40\ub3d9\uc131 \uc774\ubbf8\uc9c0 \uc624\ud574 \ub9ce\uc544\u201d (\ub9cc\uc2e0\ud3ec\ucc28) - \uc870\uc120\uc77c\ubcf4 - \uc870\uc120\uc77c\ubcf4", "description": "[\uc2a4\ud3ec\uce20\uc870\uc120\ub2f7\ucef4 \ubc15\uc544\ub78c \uae30\uc790] \uc804 \uc1fc\ud2b8\ud2b8\ub799 \uc120\uc218 \uae40\ub3d9\uc131\uc774 \ubc30\ub4dc\ud30c\ub354\uc2a4 \ub17c\ub780\uc744 \uc5b8\uae09\ud558\uba70 \uc790\uc2e0\uc758 \uc785\uc7a5\uc744 \ubc1d\ud614\ub2e4. \uc9c0\ub09c 9\uc77c \uc720\ud29c\ube0c\ucc44\ub110 \ubca0\uc9f1\uc774\uc5d4\ud130\ud14c\uc778\uba3c\ud2b8 \uc608\ub2a5 '\ub9cc\uc2e0\ud3ec\ucc28'\uc5d0\uc11c\ub294 '\uae40\ub3d9\uc131! \ucd5c\uc21c\uc2e4 \uc9d1\uc5d0\uc11c \ub3d9\uac70!? \uc591\uc721\ube44 \uc18c\uc1a1\uacfc \ubc30\ub4dc\ud30c\ub354\uc2a4\uc758 \uc804\ub9d0 \ub4f1\ub4f1'\uc774\ub77c\ub294 \uc81c\ubaa9\uc758 \uc601\uc0c1\uc774 \uac8c\uc7ac\ub410\ub2e4. \uc601\uc0c1\uc5d0\uc11c \uae40\ub3d9\uc131\uc740 \ubc30\ub4dc\ud30c\ub354\uc2a4\uc5d0 \ub300\ud55c \uc774\uc57c\uae30\uac00 \ub098\uc624\uc790 \ud55c\uc228\uc744 \ud479 \uc26c\uba70 \"\uc81c\uac00 \ub538\uacfc \uc544\ub4e4", "url": "https://www.chosun.com/entertainments/entertain_photo/2021/07/11/WATVYDUEGG6NU6SFTBRP7DXHVA/", "urlToImage": "https://images.chosun.com/resizer/Yd2KD5MIC1sx74ajSADXF7xNuWA=/640x336/smart/cloudfront-ap-northeast-1.images.arcpublishing.com/chosun/N77V3WMWFIRVGQDDGMMPOUXWBY.jpg", "publishedAt": "2021-07-11T01:10:05Z", "content": null}, {"source": {"id": null, "name": "Yna.co.kr"}, "author": "\uc548\ud64d\uc11d", "title": "55\ub144 \uc804 \uc6d4\ub4dc\ucef5 \uc6b0\uc2b9 \ub5a0\uc62c\ub9b0 \uc601\uad6d \uc5ec\uc655\u2026'\uc720\ub85c \uc6b0\uc2b9 \uac11\uc2dc\ub2e4!' - \uc5f0\ud569\ub274\uc2a4", "description": "(\uc11c\uc6b8=\uc5f0\ud569\ub274\uc2a4) \uc548\ud64d\uc11d \uae30\uc790 = \uc5d8\ub9ac\uc790\ubca0\uc2a4 2\uc138 \uc601\uad6d \uc5ec\uc655\uc774 \uc6d4\ub4dc\ucef5 \uc6b0\uc2b9 \ud2b8\ub85c\ud53c\ub97c \uc218\uc5ec\ud588\ub358 55\ub144 \uc804 \uae30\uc5b5\uc744 \ub418\uc0c8\uae30\uba70 \uc789\uae00\ub79c\ub4dc \ucd95\uad6c\ub300\ud45c\ud300\uc758 '...", "url": "https://www.yna.co.kr/view/AKR20210711016400007", "urlToImage": "https://img4.yna.co.kr/photo/ap/2021/07/11/PAP20210711045201055_P4.jpg", "publishedAt": "2021-07-11T01:10:04Z", "content": "2 [AFP=]\r\n(=) = 2 55 '' .\r\n BBC 2020 ( 2020) 11( ) .\r\n \" 55 \" \" , \" .\r\n1952 70 .\r\n[AP=]\r\n1966 . \r\n .\r\n , .\r\n \" \" .\r\n (FA) .\r\n \" \" \" \" ''.\r\n \" \" \" \" . \r\n 12 4 ' ' .\r\n ahs@yna.co.kr\r\n&lt;(c) , - &gt;20\u2026 [+13 chars]"}, {"source": {"id": null, "name": "Sbs.co.kr"}, "author": "\uad8c\uc885\uc624 \uae30\uc790", "title": "\ubc14\ud2f0, \uc714\ube14\ub358 \ud14c\ub2c8\uc2a4 \uc5ec\uc790 \ub2e8\uc2dd \uc6b0\uc2b9\u2026\ub450 \ubc88\uc9f8 \uba54\uc774\uc800 \uc6b0\uc2b9 \ud30c\ud2f0 - SBS \ub274\uc2a4", "description": "\uc560\uc290\ub9ac \ubc14\ud2f0\uac00 \uc714\ube14\ub358 \ud14c\ub2c8\uc2a4 \ub300\ud68c(\ucd1d\uc0c1\uae08 3\ucc9c501\ub9cc 6\ucc9c \ud30c\uc6b4\ub4dc\u00b7\uc57d 549\uc5b5 9\ucc9c\ub9cc \uc6d0) \uc5ec\uc790 \ub2e8\uc2dd \uc6b0\uc2b9\uc744 \ucc28\uc9c0\ud588\uc2b5\ub2c8\ub2e4. \ubc14\ud2f0\ub294 10\uc77c \uc601\uad6d \ub7f0\ub358 \uc714\ube14\ub358\uc758 \uc62c\uc789\uae00\ub79c\ub4dc\ud074\ub7fd\uc5d0\uc11c \uc5f4\ub9b0 \ub300\ud68c 12\uc77c\uc9f8 \uc5ec\uc790 \ub2e8\uc2dd \uacb0\uc2b9\uc5d0\uc11c \uce74\ub864\ub9ac\ub098 \ud50c\ub9ac\uc2a4\ucf54\ubc14\ub97c 2\ub300 1(6-3 6-7<4-7> 6-3)\ub85c \uc81c\uc555\ud588\uc2b5\ub2c8\ub2e4.", "url": "https://news.sbs.co.kr/news/endPage.do?news_id=N1006387397", "urlToImage": "https://img.sbs.co.kr/newimg/news/20210711/201569855_1280.jpg", "publishedAt": "2021-07-11T00:38:00Z", "content": "(1\u00b7) ( 3501 6 \u00b7 549 9 ) .\r\n 10() 12 (13\u00b7) 2 1(6-3 6-7&lt;4-7&gt; 6-3) .\r\n2019 .\r\n170 , 26 9 .\r\n1980 41 .\r\n2019 9 1 28 6 3 .\r\n2 .\r\n3 1 .\r\n3 0 .\r\n166 186 20 (WTA) 209 .\r\n2014 2016 .\r\n9 ' '.\r\n2011 , 10 \u2026 [+69 chars]"}, {"source": {"id": null, "name": "Mt.co.kr"}, "author": "\ud64d\ud6a8\uc9c4", "title": "\uc7a5\uc560\uc778 \ub178\ub974\ub515\uc2a4\ud0a4 \uac04\ud310 \uc11c\ubcf4\ub77c\ubbf8, \uc784\uc2e0\uc911 \uc2ec\uc7a5\ub9c8\ube44\ub85c \ubcc4\uc138 - \uba38\ub2c8\ud22c\ub370\uc774", "description": "\ud55c\uad6d \uc5ec\uc790 \uc7a5\uc560\uc778 \ub178\ub974\ub515\uc2a4\ud0a4\uc758 \uac04\ud310\uc73c\ub85c \ubd88\ub9b0 \uc11c\ubcf4\ub77c\ubbf8 \uc120\uc218\uac00 \ud5a5\ub144 35\uc138\ub85c \ubcc4\uc138\ud588\ub2e4.\uc9c0\ub09c 10\uc77c \ub300\ud55c\uc7a5\uc560\uc778\uccb4\uc721\ud68c\uc5d0 \ub530\ub974\uba74 \uc11c\ubcf4\ub77c\ubbf8\ub294 \uc804\ub0a0\uc778 9\uc77c \uc790\ud0dd\uc5d0\uc11c \uc138\uc0c1\uc744 \ub5a0\ub0ac...", "url": "https://news.mt.co.kr/mtview.php?no=2021071107321823909", "urlToImage": "https://thumb.mt.co.kr/21/2021/07/2021071107321823909_1.jpg", "publishedAt": "2021-07-10T22:42:48Z", "content": null}, {"source": {"id": null, "name": "Yna.co.kr"}, "author": "\ucd5c\uc778\uc601", "title": "\uc784\uc131\uc7ac, \uc874\ub514\uc5b4 \ud074\ub798\uc2dd 3R 2\uc5b8\ub354\ud30c\u2026\uacf5\ub3d9 29\uc704\ub85c 5\uacc4\ub2e8\u2193 - \uc5f0\ud569\ub274\uc2a4", "description": "(\uc11c\uc6b8=\uc5f0\ud569\ub274\uc2a4) \ucd5c\uc778\uc601 \uae30\uc790 = \uc784\uc131\uc7ac(23)\uac00 \ubbf8\uad6d\ud504\ub85c\uace8\ud504(PGA) \ud22c\uc5b4 \uc874\ub514\uc5b4 \ud074\ub798\uc2dd(\ucd1d\uc0c1\uae08 620\ub9cc \ub2ec\ub7ec) \uc14b\uc9f8 \ub0a0 \uacf5\ub3d9 29\uc704\ub85c \uc21c\uc704\uac00...", "url": "https://www.yna.co.kr/view/AKR20210711005800007", "urlToImage": "https://img8.yna.co.kr/photo/etc/gt/2021/07/08/PGT20210708131701055_P4.jpg", "publishedAt": "2021-07-10T22:33:00Z", "content": "[/AFP= ]\r\n(=) = (23) (PGA) ( 620 ) 29 .\r\n 11() TPC (71\u00b77268) 3 5 , 1 1 2 .\r\n 9 204 24 29 5 .\r\n(\u00b716 197) 7 .\r\n 3 1(4) 2(5) . 6(4) 1.5 .\r\n 9(4) . 11 30 . \r\n 12(3) 7 . 14(4) , 15(4) .\r\n 2 2 6 2 4 .\r\n 2 \u2026 [+142 chars]"}, {"source": {"id": null, "name": "Etoday.co.kr"}, "author": null, "title": "\ub9e5\uadf8\ub9ac\uac70 vs \ud3ec\uc774\ub9ac\uc5d0 3\ucc28\uc804 UFC 264 \uc911\uacc4 \uc2a4\ud3ec\ud2f0\ube44 \ub098\uc6b0\u318d\uc2a4\ud3ec\ud2f0\ube44 \uc628 - \ube44\uc988\uc5d4\ud130", "description": "[\ube44\uc988\uc5d4\ud130 \ud64d\uc9c0\ud6c8 \uae30\uc790]\u25b2\ub9e5\uadf8\ub9ac\uac70 \ud3ec\uc774\ub9ac\uc5d0 3\ucc28\uc804(\uc0ac\uc9c4\uc81c\uacf5=\uc2a4\ud3ec\ud2f0\ube44 \ub098\uc6b0)UFC 264 \ub9e5\uadf8\ub9ac\uac70 \ub300 \ud3ec\uc774\ub9ac\uc5d0 3\ucc28\uc804\uc774 \uc2a4\ud3ec\ud2f0\ube44 \ub098\uc6b0(SPOTV NOW)\uc640 \uc2a4\ud3ec\ud2f0", "url": "http://enter.etoday.co.kr/view/news_view.php?varAtcId=207861", "urlToImage": "http://img.etoday.co.kr/pto_db/2021/07/600/20210710222824_1642595_791_443.jpg", "publishedAt": "2021-07-10T22:00:00Z", "content": "[ ]\r\nUFC 264 3 (SPOTV NOW) (SPOTV ON) .11() T- UFC 264 3 .\r\n 2014 . 7 1 TKO .\r\nUFC 1 . 2014 UFC 179 1R TKO . 6 4 .\r\n \" , . . \" . \" () \" 3 . .\r\n UFC \" . \" . \" 1 \" . . . 7400 MMA 54% 46% . UFC 9 +108, \u2026 [+98 chars]"}, {"source": {"id": "google-news", "name": "Google News"}, "author": null, "title": "\ub3c4\ucfc4\uc62c\ub9bc\ud53d \ud6c4\ucfe0\uc2dc\ub9c8\ub3c4 \ubb34\uad00\uc911 \uacbd\uae30\ub85c \ubcc0\uacbd / YTN - YTN news", "description": null, "url": "https://news.google.com/__i/rss/rd/articles/CBMiK2h0dHBzOi8vd3d3LnlvdXR1YmUuY29tL3dhdGNoP3Y9bi1mY0k1TkxjUE3SAQA?oc=5", "urlToImage": null, "publishedAt": "2021-07-10T13:37:40Z", "content": null}, {"source": {"id": null, "name": "Segye.com"}, "author": "yangbs@segye.com \uc591\ub2e4\ud6c8", "title": "'\uc720\ud29c\ubc84 \ubcc0\uc2e0' \ud558\uc2b9\uc9c4, \ucf54\ub85c\ub09819 \ud655\uc9c4\u2026\u201cAZ 1\ucc28 \uc811\uc885\ubc1b\uc558\ub294\ub370\u201d - \uc138\uacc4\uc77c\ubcf4", "description": "\uc720\ud29c\ubc84\ub85c \ubcc0\uc2e0\ud55c \ub18d\uad6c\uc120\uc218 \ucd9c\uc2e0 \ud558\uc2b9\uc9c4(35)\uc774 \uc2e0\uc885 \ucf54\ub85c\ub098\ubc14\uc774\ub7ec\uc2a4 \uac10\uc5fc\uc99d(\ucf54\ub85c\ub09819) \ud655\uc9c4 \ud310\uc815\uc744 \ubc1b\uc558\ub2e4. 10\uc77c \ud558\uc2b9\uc9c4 \uc18c\uc18d\uc0ac \uccb4\ub9ac\uc26c\ube4c\ub9ac\uc9c0 \uce21\uc740 \u201c\ud558\uc2b9\uc9c4\uc774 \uc544\uc2a4\ud2b8\ub77c\uc81c\ub124\uce74 1\ucc28 \uc811\uc885\uc744 \ub9c8\ucce4\uc9c0\ub9cc \ucd5c\uadfc \ubab8\uc5d0 \uc774\uc0c1\uc744 \ub290\uaef4 \ucf54\ub85c\ub09819 \uac80\uc0ac\ub97c \ud588\uace0 \ud655\uc9c4 \ud310\uc815\uc744 \ubc1b\uc558\ub2e4\u201d\uace0 \ubc1d\ud614\ub2e4. \uc544\uc6b8\ub7ec \u201c\uc624\ub298 \uc624\uc804 \uc591\uc131 \ud310\uc815\uc744 \ubc1b\uc558\ub2e4. \ud604\uc7ac \uc790\uac00 \uaca9\ub9ac\ud558\uba70 \ubc29\uc5ed \ub2f9\uad6d\uc758 \uc9c0\uc2dc\ub97c \uae30\ub2e4\ub9ac\uace0 \uc788\ub2e4\u201d\uace0 \ubc1d\ud614\ub2e4. \ud568\uaed8 \uac80\uc0ac\ubc1b\uc740 \ud558\uc2b9\uc9c4\uc758 \uc544\ub0b4\ub294 \uc74c\uc131 \ud310\uc815\uc744 \ubc1b\uc558\ub2e4\uace0\ub3c4 \uc804\ud588\ub2e4. \ud558\uc2b9\uc9c4\uacfc \uc811\ucd09\ud55c \uc0ac\ub78c\ub4e4\u2026", "url": "https://www.segye.com/newsView/20210710504981", "urlToImage": "https://img.segye.com/content/image/2021/07/10/20210710505010.jpg", "publishedAt": "2021-07-10T13:00:00Z", "content": "' ' , 19 AZ 1 \r\n : 2021-07-10 22:00:00 : 2021-07-10 16:54:38"}, {"source": {"id": "google-news", "name": "Google News"}, "author": null, "title": "\uc784\uacbd\uc644 \ucf54\uce58 \uc544\ub4e4 \uacbd\ub0a8\uace0 \uc784\uc815\ud615 '\uc2e4\ub825\ub3c4 \ubd80\uc804\uc790\uc804' \ubb34\uc2e4\uc810 \ucf8c\ud22c - \uc2a4\ud3ec\uce20\uc870\uc120", "description": null, "url": "https://news.google.com/__i/rss/rd/articles/CBMiK2h0dHBzOi8vd3d3LnlvdXR1YmUuY29tL3dhdGNoP3Y9dUd6SkVfcGtqN03SAQA?oc=5", "urlToImage": null, "publishedAt": "2021-07-10T12:29:27Z", "content": null}, {"source": {"id": null, "name": "Chosun.com"}, "author": null, "title": "[\uc624\ud53c\uc15c]'\ucf54\ub85c\ub098 \ucd08\ube44\uc0c1' KBO\ub9ac\uadf8 10\uac1c \uad6c\ub2e8 1\uad70 \uc804\uc218\uac80\uc0ac \uc2e4\uc2dc\u2026\uc790\uac00\uac80\uc0ac \ud0a4\ud2b8 \uc9c0\uc6d0 - \uc2a4\ud3ec\uce20\uc870\uc120", "description": "[\ufffd\ubc78=\ufffd\ufffd\ufffd\ufffd\ufffd\ufffd\ufffd\ufffd\ufffd\ufffd \ufffd\u8ff5\ufffd\ufffd \ufffd\ufffd\ufffd\ufffd]KBO(\ufffd\ufffd\ufffd\ufffd \ufffd\ufffd\ufffd\ufffd\ufffd\ufffd)\ufffd\ufffd 7\ufffd\ufffd 10\ufffd\ufffd(\ufffd\ufffd), 11\ufffd\ufffd(\ufffd\ufffd) \ufffd\ufffd\ufffd\u03ff\ufffd \ufffd\ufffd\ufffd\ufffd '\ufffd\u06b7\u03b3\ufffd19 \ufffd\u06b0\ufffd\ufffd\u02fb\ufffd \u0170\u01ae'\ufffd\ufffd KBO \ufffd\ufffd\ufffd\ufffd 1\ufffd\ufffd \ufffd\ufffd \ufffd\ufffd\ufffd\ufffd\ufffd\ufffd\ufffd\ufffd \ufffd\u06b7\u03b3\ufffd19 \ufffd\ufffd\ufffd\ufffd\ufffd\u02fb\u7e26 \ufffd\u01fd\ufffd\ufffd\u0474\ufffd.\n\n\ufffd\u05b1\ufffd \ufffd\u07fb\ufffd\ufffd\ufffd KBO \ufffd\ufffd\ufffd\ufffd \ufffd\ufffd\ufffd\ufffd\ufffd\ufffd \ufffd\ufffd \ufffd\u06b7\u03b3\ufffd19 \ufffd\ufffd\u0232\ufffd\ufffd \ufffd\ufffd\ufffd\ufffd KBO\ufffd\ufffd \ufffd\ufffd \ufffd\ufffd\ufffd\ufffd \ufffd\ufffd\ufffd\ufffd\ufffd\ufffd \ufffd\ufffd\ufffd\ufffd\ufffd\ufffd\ufffd\ufffd \ufffd\ufffd \ufffd\ufffd\ufffd\u073f\ufffd \u0170\u01ae\ufffd\ufffd \ufffd\ufffd\ufffd\ufffd\ufffd\u03ff\ufffd \ufffd\ufc22\ufffd\ufffd\ufffd\ufffd \ufffd\ufffd\ufffd\ufffd\ufffd\u2026", "url": "https://sports.chosun.com/news/news.htm?id=202107110100085910005498&ServiceDate=20210710", "urlToImage": "https://sccdn.chosun.com/news/html/2021/07/10/2021071101000859100054981.jpg", "publishedAt": "2021-07-10T12:19:12Z", "content": "[= ]KBO( ) 7 10(), 11() '19 ' KBO 1 19 .KBO 19 KBO \u00f8 .\r\nKBO \u00e5 19 1 \u00fc SD() '19 ' 7() KBO KBO ., , \u00fa . , PCR , NC, KIA .\r\nKBO \u00fc\u00b0 , PCR , \u00f6 .\r\n= lunarfly@sportschosun.com"}, {"source": {"id": null, "name": "Sporbiz.co.kr"}, "author": "\ud55c\uc2a4\uacbd\uc81c-\ud55c\uad6d\uc2a4\ud3ec\uce20\uacbd\uc81c", "title": "[\ud504\ub9ac\ubbf8\uc5b4 12] 36\uc774\ub2dd 2\uc2e4\uc810\u2026 '\ud648\ub7f0 \uad70\ub2e8' \ubbf8\uad6d\ub3c4 \uc7a0\uc7ac\uc6b4 \uae40\uacbd\ubb38\ud638 '\ucca0\ubcbd\ubc29\ud328' - \ud55c\uad6d\uc2a4\ud3ec\uce20\uacbd\uc81c", "description": "\uae40\uacbd\ubb38\ud638\uc758 \ucca0\ubcbd \ubc29\ud328\ub294 '\ud648\ub7f0 \uad70\ub2e8' \ubbf8\uad6d\uc758 \ubd88\ub9dd\ubc29\uc774\ub3c4 \ub9c9\uc544\ub0c8\ub2e4.\uae40\uacbd\ubb38(61) \uac10\ub3c5\uc774 \uc774\ub044\ub294 \ud55c\uad6d \uc57c\uad6c \ub300\ud45c\ud300\uc740 11\uc77c \uc77c\ubcf8 \ub3c4\ucfc4\ub3d4\uc11c \uc5f4\ub9b0 2019 \uc138\uacc4\uc57c\uad6c\uc18c\ud504\ud2b8\ubcfc\uc5f0\ub9f9(WBSC) \uc288\ud37c\ub77c\uc6b4\ub4dc \ubbf8\uad6d\uacfc \uccab \uacbd\uae30\uc11c 5-1\ub85c \uc774\uacbc\ub2e4.\ucca0\uc639\uc131 \uac19\uc740 \uc704\ub825\uc744 \uc790\ub791\ud558\ub294 \ud22c\uc218\uc9c4\uc774 \uc774\ub0a0\ub3c4", "url": "https://www.sporbiz.co.kr/article/20191111499286", "urlToImage": "https://cdn1.sporbiz.co.kr/data2/content/image/2019/11/11/.cache/512/20191111289931.png", "publishedAt": "2021-07-10T09:39:00Z", "content": "ArticleVO(id=20191111499286, title=[ 12] 36 2 , subTitle=null, viewTitle=[ 12] 36 2 , viewSubTitle=null, mobileTitle=[ 12] 36 2 , mobileSubTitle=null, newsstandTitle=[ 12] 36 2 , newsstandXMLTitle=[ \u2026 [+3534 chars]"}, {"source": {"id": "google-news", "name": "Google News"}, "author": null, "title": "\ub450\uc0b0 LG \ud0a4\uc6c0 1\ucc28\uc9c0\uba85 \uc720\ub825\ud6c4\ubcf4 , \uace0\uad50 \ucd5c\uace0 \uc88c\uc644 \uc870\uc6d0\ud0dc\uc758 105\uad6c \uc5ed\ud22c - \uc2a4\ud3ec\uce20\uc870\uc120", "description": null, "url": "https://news.google.com/__i/rss/rd/articles/CBMiK2h0dHBzOi8vd3d3LnlvdXR1YmUuY29tL3dhdGNoP3Y9LThhRGlHNDg4NmfSAQA?oc=5", "urlToImage": null, "publishedAt": "2021-07-10T07:44:51Z", "content": null}, {"source": {"id": "google-news", "name": "Google News"}, "author": null, "title": "'\uc2e4\uc218\ub97c \uc904\uc774\uc790' \uc0bc\uc131 \uae40\uc9c0\ucc2c, \uc870\ub3d9\ucc2c \ucf54\uce58\uc640 2\ub8e8 \uc218\ube44 \ud2b9\ud6c8 - \uc2a4\ud3ec\uce20\uc870\uc120", "description": null, "url": "https://news.google.com/__i/rss/rd/articles/CBMiK2h0dHBzOi8vd3d3LnlvdXR1YmUuY29tL3dhdGNoP3Y9WGtKRVF3aWEzZnfSAQA?oc=5", "urlToImage": null, "publishedAt": "2021-07-10T07:21:11Z", "content": null}, {"source": {"id": null, "name": "Sporbiz.co.kr"}, "author": "\ud55c\uc2a4\uacbd\uc81c-\ud55c\uad6d\uc2a4\ud3ec\uce20\uacbd\uc81c", "title": "[MLB] \ucd94\uc2e0\uc218, 4\ud0c0\uc218 \ubb34\uc548\ud0c0... \uc5f0\uc18d \ucd9c\ub8e8 \ud589\uc9c4 '52\uacbd\uae30'\ub85c \ub9c8\uac10 - \ud55c\uad6d\uc2a4\ud3ec\uce20\uacbd\uc81c", "description": "[\ud55c\uad6d\uc2a4\ud3ec\uce20\uacbd\uc81c=\uae40\uc758\uae30 \uae30\uc790]\ucd94\uc2e0\uc218(36\u318d\ud14d\uc0ac\uc2a4 \ub808\uc778\uc800\uc2a4)\uac0053\uacbd\uae30\uc5f0\uc18d \ucd9c\ub8e8\ud589\uc9c4\uc5d0 \ub3c4\uc804\ud588\uc73c\ub098 \ubd88\ubc1c\ub410\ub2e4. \uadf8\uc758 \uae30\ub85d\uc740 52\uacbd\uae30\uc5d0\uc11c \uba48\ucdb0\uc130\ub2e4.\ucd94\uc2e0\uc218\ub294 21\uc77c(\ud604\uc9c0\uc2dc\uac04) \ubbf8\uad6d \ud14d\uc0ac\uc2a4\uc8fc \uc54c\ub9c1\ud134 \uae00\ub85c\ube0c \ub77c\uc774\ud504 \ud30c\ud06c\uc5d0\uc11c \uc5f4\ub9b0 2018 \ubbf8\uad6d\ud504\ub85c\uc57c\uad6c \uba54\uc774\uc800\ub9ac\uadf8 \ud074\ub9ac\ube14\ub79c\ub4dc\uc804\uc5d0\uc11c 1\ubc88", "url": "https://www.sporbiz.co.kr/article/20180722429162", "urlToImage": "https://cdn1.sporbiz.co.kr/data2/content/image/2018/07/22/.cache/512/20180722198978.jpg", "publishedAt": "2021-07-10T03:57:00Z", "content": "ArticleVO(id=20180722429162, title=[MLB] , 4 ... '52' , subTitle=null, viewTitle=[MLB] , 4 ... '52' , viewSubTitle=null, mobileTitle=[MLB] , 4 ... '52' , mobileSubTitle=null, newsstandTitle=[MLB] , 4\u2026 [+2701 chars]"}, {"source": {"id": null, "name": "Sporbiz.co.kr"}, "author": "\ud55c\uc2a4\uacbd\uc81c-\ud55c\uad6d\uc2a4\ud3ec\uce20\uacbd\uc81c", "title": "\ucd5c\uc7ac\uc6b0, \ud55c\uad6d \uc2a4\ud0a4 \ud76c\ub9dd\uc5d0\uc11c \uc601\uad6c \uc81c\uba85\uae4c\uc9c0 '\ud55c \ub2ec' - \ud55c\uad6d\uc2a4\ud3ec\uce20\uacbd\uc81c", "description": "[\ud55c\uad6d\uc2a4\ud3ec\uce20\uacbd\uc81c \uae40\uc758\uae30]\ucd5c\uadfc \uc0ac\ud68c \uc804\ubc18\uc744 \ud729\uc4f8\uace0 \uc788\ub294 \uc131\ucd94\ubb38 \ud30c\ubb38\uc774 \uccb4\uc721\uacc4\ub85c\ub3c4 \uc62e\uaca8 \ubd99\uc5c8\ub2e4. \ubd88\ubbf8\uc2a4\ub7ec\uc6b4 \uc0ac\uac74\uc758 \uc8fc\uc778\uacf5\uc740 \ubaa8\uad74 \uc2a4\ud0a4 \uad6d\uac00\ub300\ud45c\ub85c 2018 \ud3c9\ucc3d \ub3d9\uacc4\uc62c\ub9bc\ud53d\uc5d0 \ucd9c\uc804\ud55c \ucd5c\uc7ac\uc6b0(24\ud55c\uad6d\uccb4\ub300)\uc640 \ud504\ub9ac\uc2a4\ud0c0\uc77c \uc2a4\ud0a4 \uad6d\uac00\ub300\ud45c \uae40\uc9c0\ud5cc(23GKL)\uc774\ub2e4.\ub300\ud55c\uc2a4\ud0a4\ud611\ud68c\ub294 14\uc77c", "url": "https://www.sporbiz.co.kr/article/20180315408303", "urlToImage": "https://cdn1.sporbiz.co.kr/data2/content/image/2018/03/15/.cache/512/20180315173018.jpg", "publishedAt": "2021-07-09T18:04:00Z", "content": "ArticleVO(id=20180315408303, title=, ' ', subTitle=null, viewTitle=, ' ', viewSubTitle=null, mobileTitle=, ' ', mobileSubTitle=null, newsstandTitle=, ' ', newsstandXMLTitle=, ' ', imgSrc=/content/ima\u2026 [+2937 chars]"}, {"source": {"id": null, "name": "Sporbiz.co.kr"}, "author": "\ud55c\uc2a4\uacbd\uc81c-\ud55c\uad6d\uc2a4\ud3ec\uce20\uacbd\uc81c", "title": "\uc815\ud604 vs \uc0cc\ub4dc\uadf8\ub80c, '\uc9c4\uc9dc' \ub3cc\ud48d\uc758 \uc8fc\uc778\uacf5 \uac00\ub9b0\ub2e4 - \ud55c\uad6d\uc2a4\ud3ec\uce20\uacbd\uc81c", "description": "[\ud55c\uad6d\uc2a4\ud3ec\uce20\uacbd\uc81c \uae40\uc8fc\ud76c]'\ub3cc\ud48d'\uacfc '\ub3cc\ud48d'\uc774 \ub9de\ubd99\ub294\ub2e4. \ud55c\uad6d\uc778 \ucd5c\ucd08\ub85c \uba54\uc774\uc800 \ub300\ud68c 8\uac15\uc5d0 \uc624\ub978 \uc815\ud604(2258\uc704\uc0bc\uc131\uc99d\uad8c \ud6c4\uc6d0)\uc774 \ub0b4\uce5c\uae40\uc5d0 4\uac15\uae4c\uc9c0 \ub118\ubcf8\ub2e4. \uc774\ubc88 \ub300\ud68c \ub300\uc774\ubcc0\uc744 \uc4f0\uace0 \uc788\ub294 \ud14c\ub2c8\uc2a4 \uc0cc\ub4dc\uadf8\ub80c(2797\uc704\ubbf8\uad6d)\uc744 \ubb3c\ub9ac\uce58\uba74 \ub610 \ud55c \ubc88 \uc0c8 \uc5ed\uc0ac\uac00 \uc5f4\ub9b0\ub2e4.\uc815\ud604\uc740 22\uc77c", "url": "https://www.sporbiz.co.kr/article/20180123400414", "urlToImage": "https://cdn1.sporbiz.co.kr/data2/content/image/2018/01/23/.cache/512/20180123162591.jpg", "publishedAt": "2021-07-09T17:43:00Z", "content": "ArticleVO(id=20180123400414, title= vs , '' , subTitle=null, viewTitle= vs , '' , viewSubTitle=null, mobileTitle= vs , '' , mobileSubTitle=null, newsstandTitle= vs , '' , newsstandXMLTitle= vs , '' ,\u2026 [+3380 chars]"}, {"source": {"id": null, "name": "Sporbiz.co.kr"}, "author": "\ud55c\uc2a4\uacbd\uc81c-\ud55c\uad6d\uc2a4\ud3ec\uce20\uacbd\uc81c", "title": "\uae40\ubcf4\ub984-\ub178\uc120\uc601 \uae4a\uc5b4\uc9c4 \uac08\ub4f1\uc758 \uace8, \uc5f0\ub9f9 \"14\uc77c \uc774\ud6c4 \uc785\uc7a5 \ubc1c\ud45c\" - \ud55c\uad6d\uc2a4\ud3ec\uce20\uacbd\uc81c", "description": "[\ud55c\uad6d\uc2a4\ud3ec\uce20\uacbd\uc81c=\uc774\uc0c1\ube48 \uae30\uc790]2018 \ud3c9\ucc3d \ub3d9\uacc4\uc62c\ub9bc\ud53d \uc2a4\ud53c\ub4dc \uc2a4\ucf00\uc774\ud305 \uc5ec\uc790 \ud300 \ucd94\uc6d4 \uc885\ubaa9\uc5d0 \ub098\uc130\ub358 \uae40\ubcf4\ub984(26\u318d\uac15\uc6d0\ub3c4\uccad)\uc774 11\uc77c \ubc29\uc1a1\ud55c \ucc44\ub110A '\ub274\uc2a4 LIVE'\uc5d0\uc11c \"\ub178\uc120\uc601(30)\uc5d0\uac8c \uad34\ub86d\ud798\uc744 \ub2f9\ud55c \ud53c\ud574\uc790\"\ub77c\uace0 \ud3ed\ub85c\ud588\ub2e4. \ub450 \uc0ac\ub78c \uc0ac\uc774 \uc8fc\uc7a5\uc774 \uc5c7\uac08\ub9ac\uba70 \uac08\ub4f1\uc758 \uace8\uc774 \ub354", "url": "https://www.sporbiz.co.kr/article/20190111451225", "urlToImage": "https://cdn1.sporbiz.co.kr/data2/content/image/2019/01/11/.cache/512/20190111228656.jpg", "publishedAt": "2021-07-09T14:51:00Z", "content": "ArticleVO(id=20190111451225, title=- , \"14 \", subTitle=null, viewTitle=- , \"14 \", viewSubTitle=null, mobileTitle=- , \"14 \", mobileSubTitle=null, newsstandTitle=- , \"14 \", newsstandXMLTitle=- , \"14 \",\u2026 [+2879 chars]"}, {"source": {"id": null, "name": "Sporbiz.co.kr"}, "author": "\ud55c\uc2a4\uacbd\uc81c-\ud55c\uad6d\uc2a4\ud3ec\uce20\uacbd\uc81c", "title": "\uc1fc\ud2b8\ud2b8\ub799, \uad6d\uac00\ub300\ud45c \uba54\ub2ec\ub9ac\uc2a4\ud2b8 \ub4f1 \uc120\uc218\ucd0c\uc11c \uc804\uc6d0 \ud1f4\ucd0c \uacb0\uc815 - \ud55c\uad6d\uc2a4\ud3ec\uce20\uacbd\uc81c", "description": "[\ud55c\uad6d\uc2a4\ud3ec\uce20\uacbd\uc81c=\uc870\uc131\uc9c4 \uae30\uc790] \uc1fc\ud2b8\ud2b8\ub799 \uad6d\uac00\ub300\ud45c\ud300 \uc804\uc6d0\uc774 \uc9d1\ub2e8 \ud1f4\ucd0c \ub2f9\ud560 \uac83 \uc73c\ub85c \ubcf4\uc778\ub2e4. \uc9c0\ub09c 24\uc77c \ub300\ud55c\uccb4\uc721\ud68c\ub294 \uc1fc\ud2b8\ud2b8\ub799 \ub0a8\uc790 \ub300\ud45c\ud300 7\uba85, \uc5ec\uc790\ub300\ud45c\ud300 7\uba85 \ucd1d 14\uba85\uc744 \ud6c8\ub828 \uae30\uac15 \ud574\uc774\uc5d0 \ub300\ud55c \ubb38\ucc45\uc73c\ub85c \uc804\uc6d0 \ud1f4\ucd9c \uacb0\uc815\ud588\ub2e4.\uc9c0\ub09c 17\uc77c \uc9c4\ucc9c\uc120\uc218\ucd0c\uc5d0\uc11c \uc554\ubcbd\ub4f1\ubc18 \ud6c8\ub828 \ub3c4", "url": "https://www.sporbiz.co.kr/article/20190625476480", "urlToImage": "https://cdn1.sporbiz.co.kr/data2/content/image/2019/06/25/.cache/512/20190625261149.jpg", "publishedAt": "2021-07-09T12:50:00Z", "content": "ArticleVO(id=20190625476480, title=, , subTitle=, , viewTitle=, , viewSubTitle=, , mobileTitle=, , mobileSubTitle=, , newsstandTitle=, , newsstandXMLTitle=, , imgSrc=/content/image/2019/06/25/2019062\u2026 [+7043 chars]"}, {"source": {"id": "google-news", "name": "Google News"}, "author": null, "title": "[\ub2e8\ub3c5] \ub9de\uc544\uc11c \uce58\uc544 \ubd80\ub7ec\uc84c\ub294\ub370\u2026\uac10\ub3c5\uc740 \"\ub118\uc5b4\uc838\uc11c\" / SBS - SBS \ub274\uc2a4", "description": null, "url": "https://news.google.com/__i/rss/rd/articles/CBMiK2h0dHBzOi8vd3d3LnlvdXR1YmUuY29tL3dhdGNoP3Y9djRnRjZudUpQOXfSAQA?oc=5", "urlToImage": null, "publishedAt": "2021-07-09T11:38:52Z", "content": null}, {"source": {"id": "google-news", "name": "Google News"}, "author": null, "title": "\ud504\ub85c\ub18d\uad6c 2021-2022 \uc2dc\uc98c 10\uc6d4 9\uc77c \uac1c\ub9c9\u2026\ud559\ud3ed \uad00\ub828 \uaddc\uc815 \uc2e0\uc124 / \uc5f0\ud569\ub274\uc2a4TV (YonhapnewsTV) - \uc5f0\ud569\ub274\uc2a4TV", "description": null, "url": "https://news.google.com/__i/rss/rd/articles/CBMiK2h0dHBzOi8vd3d3LnlvdXR1YmUuY29tL3dhdGNoP3Y9MGY5aS1Id3Rfb0HSAQA?oc=5", "urlToImage": null, "publishedAt": "2021-07-09T09:16:58Z", "content": null}, {"source": {"id": "google-news", "name": "Google News"}, "author": null, "title": "\uc911\uc559\uace0\uc758 10\ub3000 \ucf5c\ub4dc\uac8c\uc784 \uc2b9 \uc774\ub048 \uc591\uc778\ud601\uc758 \ubb35\uc9c1\ud55c \uc9c1\uad6c - \uc2a4\ud3ec\uce20\uc870\uc120", "description": null, "url": "https://news.google.com/__i/rss/rd/articles/CBMiK2h0dHBzOi8vd3d3LnlvdXR1YmUuY29tL3dhdGNoP3Y9NWpEdm50VlNUb1HSAQA?oc=5", "urlToImage": null, "publishedAt": "2021-07-09T09:04:19Z", "content": null}, {"source": {"id": "google-news", "name": "Google News"}, "author": null, "title": "[\ube44\uc988&] LG\uc804\uc790, \uc790\ud3d0\uc544\ub3d9 \uc704\ud55c \uc790\uc120\uacbd\ub9e4\u2026'\uc2dc\uadf8\ub2c8\ucc98 \uc62c\ub808\ub4dc R' / \uc5f0\ud569\ub274\uc2a4TV (YonhapnewsTV) - \uc5f0\ud569\ub274\uc2a4TV", "description": null, "url": "https://news.google.com/__i/rss/rd/articles/CBMiK2h0dHBzOi8vd3d3LnlvdXR1YmUuY29tL3dhdGNoP3Y9MHVNV1g5VDU0YXfSAQA?oc=5", "urlToImage": null, "publishedAt": "2021-07-09T08:43:30Z", "content": null}, {"source": {"id": null, "name": "Nocutnews.co.kr"}, "author": "\uc784\uc885\ub960", "title": "'\uc5ed\uc2dc \uce84\ubcf4\ub514\uc544 \ud2b9\uae09' \ud53c\uc544\ube44, \ud37c\ud399\ud2b8 \ud050\ub85c \ub300\uc5ed\uc804\uadf9 - \ub178\ucef7\ub274\uc2a4", "description": "'\uce84\ubcf4\ub514\uc544 \ud2b9\uae09' \uc2a4\ub871 \ud53c\uc544\ube44(\ube14\ub8e8\uc6d0\ub9ac\uc870\ud2b8)\uac00 \uc62c \uc2dc\uc98c \ucc98\uc74c\uc73c\ub85c '\ud37c\ud399\ud2b8 \ud050'\ub97c \ub2ec\uc131\ud558\uba70 \uc544\ub9c8\ucd94\uc5b4 \ucd5c\uac15\uc758 \uc874\uc7ac\uac10\uc744 \ubf50\ub0c8\ub2e4. \ud53c\uc544\ube44\ub294 9\uc77c \uacbd\uae30\ub3c4 \uace0\uc591\uc2dc \ube5b\ub9c8\ub8e8\ubc29\uc1a1\uc13c\ud130\uc5d0\uc11c \uc5f4\ub9b0 '\uc6f0\ucef4\uc800\ucd95\uc740\ud589 PBA \ud300 \ub9ac\uadf8 2021-2..", "url": "https://www.nocutnews.co.kr/news/5586081", "urlToImage": "https://file2.nocutnews.co.kr/newsroom/image/2021/07/09/202107091709093798_0.jpg", "publishedAt": "2021-07-09T08:09:00Z", "content": "' ' () ' ' .9 ' PBA 2021-22' 1 4 2 11 . 0 9 11 11 .\r\nPBA . PBA 1000 . () .\r\n. PBA ' PBA-LPBA ' 1 4 PBA .\r\n10 . 9 .\r\n. 11 3 . , , 2 .\r\n. 10 . .\r\n. 3 3 3 (1) .\r\n\"1 0 15 2 0 \" \" ( ) \" . \" \" .2 2 4 . 19 \u2026 [+15 chars]"}, {"source": {"id": null, "name": "Sporbiz.co.kr"}, "author": "\ud55c\uc2a4\uacbd\uc81c-\ud55c\uad6d\uc2a4\ud3ec\uce20\uacbd\uc81c", "title": "\uc870\ub3d9\ucc2c 1\ud68c \uc0ac\uad6c\uac00 \uc0bc\uc131-\ud55c\ud654 \ub09c\ud22c\uadf9\uc758 '\uc2dc\ubc1c\uc810'? - \ud55c\uad6d\uc2a4\ud3ec\uce20\uacbd\uc81c", "description": "[\ud55c\uad6d\uc2a4\ud3ec\uce20\uacbd\uc81c \uae40\uc815\ud76c]KBO \uc0ac\uc0c1 \uccab \uc591\ud300 \uc120\ubc1c\ud22c\uc218\uac00 \ub3d9\uc2dc \ud1f4\uc7a5 \ub2f9\ud55c \ub09c\ud22c\uadf9\uc758 \uc2dc\ubc1c\uc810\uc774 \uc870\ub3d9\ucc2c\uc758 1\ud68c \uc0ac\uad6c\ub85c \uc9c0\ubaa9\ub410\ub2e4.21\uc77c \ub300\uc804 \uad6c\uc7a5\uc5d0\uc11c \uc5f4\ub9b0 \uc0bc\uc131-\ud55c\ud654 \uacbd\uae30\uc5d0\uc11c \uc5f0\uc774\uc740 \uc0ac\uad6c\ub85c \ub450 \ucc28\ub840 \ubca4\uce58\ud074\ub9ac\uc5b4\ub9c1\uc774 \ubc1c\uc0dd\ud588\ub2e4. \uacb0\uad6d \uc0bc\uc131 \uc120\ubc1c \uc724\uc131\ud658\uacfc \ud398\ud2b8\ub9ad, \ud55c\ud654 \uc120\ubc1c \ube44\uc57c\ub204\uc5d0\ubc14", "url": "https://www.sporbiz.co.kr/article/20170522308301", "urlToImage": "https://cdn1.sporbiz.co.kr/data2/content/image/2017/05/22/.cache/512/20170522115211.jpg", "publishedAt": "2021-07-09T07:51:00Z", "content": "ArticleVO(id=20170522308301, title= 1 - ?, subTitle=null, viewTitle= 1 - ?, viewSubTitle=null, mobileTitle= 1 - ?, mobileSubTitle=null, newsstandTitle= 1 - ?, newsstandXMLTitle= 1 - ?, imgSrc=/conten\u2026 [+2362 chars]"}, {"source": {"id": null, "name": "Sporbiz.co.kr"}, "author": "\ud55c\uc2a4\uacbd\uc81c-\ud55c\uad6d\uc2a4\ud3ec\uce20\uacbd\uc81c", "title": "\ub9c8\uc9c0\ub9c9 \uc62c\ub9bc\ud53d \uc55e\ub454 \uae40\uc5f0\uacbd \u201c\ub3c4\ucfc4\uc62c\ub9bc\ud53d \uc5f0\uae30 \ub2f9\uc5f0\ud55c \uacb0\uc815, \uc798 \uc900\ube44 \ud560 \uac83\u201d - \ud55c\uad6d\uc2a4\ud3ec\uce20\uacbd\uc81c", "description": "\ub9c8\uc9c0\ub9c9 \uc62c\ub9bc\ud53d\uc744 \uc55e\ub454 \ubc30\uad6c\uc5ec\uc81c \uae40\uc5f0\uacbd(32\u318d\uc5d1\uc790\uc2dc\ubc14\uc2dc)\uc774 \ub3c4\ucfc4\uc62c\ub9bc\ud53d \uc5f0\uae30\uc5d0 \ub2f4\ub2f4\ud55c \uc2ec\uacbd\uc744 \uc804\ud558\uba70 \ub2e4\uc2dc \ud55c\ubc88 \uac01\uc624\ub97c \ub2e4\uc84c\ub2e4.\uae40\uc5f0\uacbd\uc740 25\uc77c(\uc774\ud558 \ud55c\uad6d \uc2dc\uac01) \uc18c\uc18d\uc0ac \ub77c\uc774\uc5b8\uc573\uc744 \ud1b5\ud574 \ub3c4\ucfc4\uc62c\ub9bc\ud53d\uc774 \uc5f0\uae30\ub420 \uac83\uc774\ub77c\uace0 \uc608\uc0c1\uc740 \ud588\uc9c0\ub9cc \uc2e4\uc81c\ub85c \uc5f0\uae30 \uc18c\uc2dd\uc744 \ub4e4\uc73c\ub2c8 \ub2f9\ud639\uc2a4\ub7ec\uc6b4 \ubd80\ubd84\uc774 \uc788", "url": "https://www.sporbiz.co.kr/article/20200325103833", "urlToImage": "https://cdn1.sporbiz.co.kr/data2/content/image/2020/03/25/.cache/512/20200325314246.png", "publishedAt": "2021-07-09T07:27:00Z", "content": "ArticleVO(id=20200325103833, title= , , subTitle=null, viewTitle= , , viewSubTitle=null, mobileTitle= , , mobileSubTitle=null, newsstandTitle= , , newsstandXMLTitle= , , imgSrc=/content/image/2020/03\u2026 [+2515 chars]"}, {"source": {"id": "google-news", "name": "Google News"}, "author": null, "title": "\uc0bc\uc131 \ubabd\uace0\uba54\ub9ac\uc758 \uce90\uce58\ubcfc, \ub0a0\uce74\ub85c\uc6b4 \ubcfc \ub05d \uc6c0\uc9c1\uc784\uc774 \uc77c\ud488! - \uc2a4\ud3ec\uce20\uc870\uc120", "description": null, "url": "https://news.google.com/__i/rss/rd/articles/CBMiK2h0dHBzOi8vd3d3LnlvdXR1YmUuY29tL3dhdGNoP3Y9OFBDaHBJZGJCTFnSAQA?oc=5", "urlToImage": null, "publishedAt": "2021-07-09T07:03:09Z", "content": null}, {"source": {"id": null, "name": "Sporbiz.co.kr"}, "author": "\ud55c\uc2a4\uacbd\uc81c-\ud55c\uad6d\uc2a4\ud3ec\uce20\uacbd\uc81c", "title": "\uc774\uc2b9\uc6b0 \ub17c\ub780, \ud1a0\ub108\uba3c\ud2b8\uc5d0\ub294 \ucd9c\uc804\ud560 \uc218 \uc788\uc744\uae4c - \ud55c\uad6d\uc2a4\ud3ec\uce20\uacbd\uc81c", "description": "[\ud55c\uad6d\uc2a4\ud3ec\uce20\uacbd\uc81c=\uc815\uaddc\ubbfc \uae30\uc790] \ud55c\uad6d\uc774 \uc544\uc2dc\uc548\ucef5 \uc911\uad6d\uc804 2-0 \uc644\uc2b9\uc5d0 \uae30\uc068\uc744 \ub9cc\ub07d\ud558\uae30\ub3c4 \uc7a0\uc2dc, \uc774\uc2b9\uc6b0\uc758 \uc77c\uba85'\ubb3c\ubcd1 \ub17c\ub780'\uc774 \uc2dd\uc744 \uc904 \ubaa8\ub974\uace0 \uc788\ub2e4.\ud55c\uad6d \ucd95\uad6c\ub300\ud45c\ud300\uc740 17\uc77c(\ud55c\uad6d\uc2dc\uac04) \uc544\ub78d\uc5d0\ubbf8\ub9ac\ud2b8 \uc544\ubd80\ub2e4\ube44\uc758 \uc54c \ub098\uc580 \uc2a4\ud0c0\ub514\uc6c0\uc5d0\uc11c \uc5f4\ub9b0 \uc911\uad6d\uacfc 2019 \uc544\uc2dc\uc544\ucd95\uad6c\uc5f0\ub9f9(AFC)", "url": "https://www.sporbiz.co.kr/article/20190117452060", "urlToImage": "https://cdn1.sporbiz.co.kr/data2/content/image/2019/01/17/.cache/512/20190117229784.jpg", "publishedAt": "2021-07-09T06:54:00Z", "content": "ArticleVO(id=20190117452060, title= , , subTitle=16 &lt;br/&gt; \" \", viewTitle= , , viewSubTitle=16 &lt;br/&gt; \" \", mobileTitle= , , mobileSubTitle=16 &lt;br/&gt; \" \", newsstandTitle= , , newsstandX\u2026 [+2539 chars]"}, {"source": {"id": null, "name": "Sporbiz.co.kr"}, "author": "\ud55c\uc2a4\uacbd\uc81c-\ud55c\uad6d\uc2a4\ud3ec\uce20\uacbd\uc81c", "title": "\uc2a4\ub9ac\ub791\uce74\uc804\uc5d0 \ub098\uc124 \ud55c\uad6d \ucd95\uad6c\uc758 \uacf5\uaca9 \uc120\ubd09\uc740 '\uc190\ud765\ubbfc\u318d\uae40\uc2e0\uc6b1\u318d\ud669\ud76c\ucc2c' - \ud55c\uad6d\uc2a4\ud3ec\uce20\uacbd\uc81c", "description": "\uc190\ud765\ubbfc(\ud1a0\ud2b8\ub118)\uacfc \uae40\uc2e0\uc6b1(\uc0c1\ud558\uc774 \uc120\ud654), \ud669\ud76c\ucc2c(\uc798\uce20\ubd80\ub974\ud06c)\uc774 \uc2a4\ub9ac\ub791\uce74\uc804\uc5d0 \ucd9c\uaca9\ud55c\ub2e4.\ud30c\uc6b8\ub8e8 \ubca4\ud22c \ud55c\uad6d \ucd95\uad6c\ub300\ud45c\ud300 \uac10\ub3c5\uc740 10\uc77c \ud654\uc131\uc885\ud569\uacbd\uae30\ud0c0\uc6b4 \uc8fc \uacbd\uae30\uc7a5\uc5d0\uc11c \uc5f4\ub9ac\ub294 \uc2a4\ub9ac\ub791\uce74\uc640 2022\ub144 \uce74\ud0c0\ub974 \uc6d4\ub4dc\ucef5 \uc544\uc2dc\uc544\uc9c0\uc5ed 2\ucc28 \uc608\uc120 H\uc870 2\ucc28\uc804\uc5d0\uc11c \uae40\uc2e0\uc6b1\uc744 \uc6d0\ud1b1 \uc2a4\ud2b8\ub77c\uc774\ucee4\ub85c \ub099\uc810", "url": "https://www.sporbiz.co.kr/article/20191010494476", "urlToImage": "https://cdn1.sporbiz.co.kr/data2/content/image/2019/10/10/.cache/512/20191010283559.jpg", "publishedAt": "2021-07-09T06:47:00Z", "content": "ArticleVO(id=20191010494476, title= '', subTitle=null, viewTitle= '', viewSubTitle=null, mobileTitle= '', mobileSubTitle=null, newsstandTitle= '', newsstandXMLTitle= '', imgSrc=/content/image/2019/10\u2026 [+2493 chars]"}, {"source": {"id": null, "name": "Koreatimes.com"}, "author": null, "title": "\ub958\ud604\uc9c4, \ubcfc\ud2f0\ubaa8\uc5b4\uc804 \uc2b9\ub9ac\u2026 \uc804\ubc18\uae30 8\uc2b9 5\ud328 ERA 3.56\uc73c\ub85c \ub9c8\uac10 - \ubbf8\uc8fc \ud55c\uad6d\uc77c\ubcf4 - \ubbf8\uc8fc \ud55c\uad6d\uc77c\ubcf4", "description": "\ub958\ud604\uc9c4(34\u00b7\ud1a0\ub860\ud1a0 \ube14\ub8e8\uc81c\uc774\uc2a4)\uc774 2021\ub144 \uc804\ubc18\uae30 \ub9c8\uc9c0\ub9c9 \ub4f1\ud310\uc5d0\uc11c \uae30\ubd84 \uc88b\uc740 \uc2b9\ub9ac\ub97c \uc548\uc558\ub2e4.\ub958\ud604\uc9c4\uc740 7\uc77c \uba54\ub9b4\ub79c\ub4dc\uc8fc \ubcfc\ud2f0\ubaa8\uc5b4\uc758 \uc624\ub9ac\uc62c \ud30c\ud06c \uc573 \ucea0\ub4e0 \uc57c\uc988\uc5d0\uc11c \ubcfc\ud2f0\ubaa8\uc5b4 \uc624\ub9ac\uc62c\uc2a4\uc640 \uce58\ub978 \ubbf8\uad6d\ud504\ub85c\uc57c\uad6c(MLB) \ubc29\ubb38 \uacbd\uae30\uc5d0 \uc120\ubc1c\ub85c \ub9c8\uc6b4\ub4dc\uc5d0 \uc62c\ub77c \ud0c8\uc0bc\uc9c4 7\uac1c\ub97c \uc18e\uc544\ub0b4\uba70 5\uc774\ub2dd \ub3d9\uc548 1\uc810\ub9cc \uc92c\ub2e4.\ub958\ud604\uc9c4\uc740 \uacf5 86\uac1c\ub97c \ub358\uc838 \uc548\ud0c0 5\uac1c, \ubcfc\ub137 2\uac1c\ub97c \ud5c8\uc6a9\ud588\ub2e4.\ud0c0\uc120\uc758 \ub109\ub109\ud55c \uc9c0\uc6d0 \ub355\ubd84\uc5d0 9-1\ub85c \uc55e\uc120 6\ud68c \uc2b9\ub9ac \ud22c\uc218 \uc694\uac74\uc744 \uc548\uace0 \uac15\ud310\ud55c \ub958\ud604\uc9c4\uc740 10-2\ub85c \uacbd\uae30\uac00 \ub05d\ub0a8\uc5d0 \ub530\ub77c\u2026", "url": "http://www.koreatimes.com", "urlToImage": "http://mimg.koreatimes.com/286/172/article/2021/07/08/20210708174743601.jpg", "publishedAt": "2021-07-09T06:41:52Z", "content": "5 7K 1\r\n 5 1 8 . []\r\n(34\u00b7 ) 2021 .7 (MLB) 7 5 1 .\r\n86 5, 2 . \r\n9-1 6 10-2 6 27 11 .\r\n17 8 5, (ERA) 3.56 .\r\n8 3 .\r\n12 17 .\r\n2 4 .\r\n. 1 19, 2 22, 3 23 .\r\n. 149 3 52% .\r\n, 42(49%), 18(21%), 16(19%), 8(9\u2026 [+58 chars]"}, {"source": {"id": null, "name": "Sporbiz.co.kr"}, "author": "\ud55c\uc2a4\uacbd\uc81c-\ud55c\uad6d\uc2a4\ud3ec\uce20\uacbd\uc81c", "title": "\ud504\ub85c\uc57c\uad6c \ud55c\ud654, \ub450\uc0b0\uc5d0 \ud328\ubc30... \uc5ed\ub300 \ucd5c\ub2e4 18\uc5f0\ud328 \ud0c0\uc774 \ubd88\uba85\uc608 - \ud55c\uad6d\uc2a4\ud3ec\uce20\uacbd\uc81c", "description": "\ud55c\ud654 \uc774\uae00\uc2a4\uac00 \ud504\ub85c\uc57c\uad6c \uc5ed\ub300 \ucd5c\ub2e4 \uc5f0\ud328 \ud0c0\uc774 \uae30\ub85d\uc744 \uc37c\ub2e4. \uadf8\uc57c\ub9d0\ub85c \uce58\uc695\uc774\ub2e4.\ud55c\ud654\ub294 12\uc77c \ub300\uc804 \ud55c\ud654\uc0dd\uba85 \uc774\uae00\uc2a4\ud30c\ud06c\uc5d0\uc11c \ud3bc\uccd0\uc9c42020 \uc2e0\ud55c\uc740\ud589 \uc3e0(SOL) KBO\ub9ac\uadf8 \ub450\uc0b0 \ubca0\uc5b4\uc2a4\uc640\ud648 \uacbd\uae30\uc5d0\uc11c 2-5\ub85c \uc84c\ub2e4.\uc9c0\ub09c\ub2ec 23\uc77c\ubd80\ud130 \uc774\ub0a0\uae4c\uc9c0 18\uc5f0\ud328\ub97c \uae30\ub85d\ud55c \ud55c\ud654\ub294 1985\ub144", "url": "https://www.sporbiz.co.kr/article/20200612006324", "urlToImage": "https://cdn1.sporbiz.co.kr/data2/content/image/2020/06/12/.cache/512/20200612329534.jpg", "publishedAt": "2021-07-09T06:11:11Z", "content": "ArticleVO(id=20200612006324, title= , ... 18 , subTitle=null, viewTitle= , ... 18 , viewSubTitle=null, mobileTitle= , ... 18 , mobileSubTitle=null, newsstandTitle= , ... 18 , newsstandXMLTitle= , ...\u2026 [+2935 chars]"}, {"source": {"id": null, "name": "Sporbiz.co.kr"}, "author": "\ud55c\uc2a4\uacbd\uc81c-\ud55c\uad6d\uc2a4\ud3ec\uce20\uacbd\uc81c", "title": "\uc774\uc815\uc7406 US\uc5ec\uc790\uc624\ud508\uace8\ud504\uc120\uc218\uad8c\ub300\ud68c \uc5ed\uc804 \uc6b0\uc2b9, LPGA \uccab \uc2b9 '\uba54\uc774\uc800\ud038' - \ud55c\uad6d\uc2a4\ud3ec\uce20\uacbd\uc81c", "description": "[\ud55c\uad6d\uc2a4\ud3ec\uce20\uacbd\uc81c=\uc2ec\uc7ac\ud76c \uae30\uc790] '\ud56b\uc2dd\uc2a4' \uc774\uc815\uc7406(23)\uc774 \ubbf8\uad6d\uc5ec\uc790\ud504\ub85c\uace8\ud504(LPGA) \uba54\uc774\uc800\ub300\ud68c\uc5d0\uc11c \uccab \uc2b9 \uc62c\ub838\ub2e4.\uc774\uc815\uc7406\uc740 3\uc77c(\ud55c\uad6d \uc2dc\uad6d) \ubbf8\uad6d \uc0ac\uc6b0\uc2a4\uce90\ub864\ub77c\uc774\ub098 \uc8fc \ucc30\uc2a4\ud134\uc758 \ucee8\ud2b8\ub9ac\ud074\ub7fd \uc624\ube0c \ucc30\uc2a4\ud134(\ud30c716535\uc57c\ub4dc)\uc5d0\uc11c \ud3bc\uccd0\uc9c4 \uc81c74\ud68c US\uc5ec\uc790\uc624\ud508\uace8\ud504\uc120\uc218\uad8c\ub300\ud68c \ucd5c\uc885", "url": "https://www.sporbiz.co.kr/article/20190603472340", "urlToImage": "https://cdn1.sporbiz.co.kr/data2/content/image/2019/06/03/.cache/512/20190603255924.jpg", "publishedAt": "2021-07-09T06:05:00Z", "content": "ArticleVO(id=20190603472340, title=6 US , LPGA '', subTitle=6, US LPGA &lt;br/&gt;6, LPGA , viewTitle=6 US , LPGA '', viewSubTitle=6, US LPGA &lt;br/&gt;6, LPGA , mobileTitle=6 US , LPGA '', mobileSu\u2026 [+3031 chars]"}]}